regression_model/__init__.py
regression_model/config.yml
regression_model/inference.py
regression_model/train.py
regression_model/version.txt
regression_model/config/__init__.py
regression_model/config/core.py
regression_model/data/link/adj.npy
regression_model/data/link/error_metrics.csv
regression_model/data/link/null.csv
regression_model/data/link/pred.npy
regression_model/data/link/result.csv
regression_model/data/link/stations
regression_model/data/link/time.csv
regression_model/data/link/time_index
regression_model/data/link/true.npy
regression_model/model/__init__.py
regression_model/model/layers.py
regression_model/model/models.py
regression_model/save_model/best_model.pth
regression_model/save_model/test_model.pth
regression_model/script/__init__.py
regression_model/script/dataloader.py
regression_model/script/earlystopping.py
regression_model/script/preprocess.py
regression_model/script/utility.py
regression_model/train_val_test/test_data.pt
regression_model/train_val_test/zscore.pt
stgcn_regression_model-0.0.5.dist-info/METADATA
stgcn_regression_model-0.0.5.dist-info/WHEEL
stgcn_regression_model-0.0.5.dist-info/top_level.txt
stgcn_regression_model-0.0.5.dist-info/RECORD
