Metadata-Version: 2.1
Name: stgcn-regression-model
Version: 0.0.5
Summary: TSB Bus ETA forecasting model
Home-page: https://github.com/kasidejcha/stgcn_deployment
Author: kasidejcha
Author-email: kasidejcha.bas@gmail.com
License: BSD-3
Classifier: License :: OSI Approved :: MIT License
Classifier: Programming Language :: Python
Classifier: Programming Language :: Python :: 3
Classifier: Programming Language :: Python :: 3.6
Classifier: Programming Language :: Python :: 3.7
Classifier: Programming Language :: Python :: 3.8
Classifier: Programming Language :: Python :: 3.9
Classifier: Programming Language :: Python :: Implementation :: CPython
Classifier: Programming Language :: Python :: Implementation :: PyPy
Requires-Python: ==3.9.13
Requires-Dist: matplotlib (==3.4.2)
Requires-Dist: numpy (==1.22.4)
Requires-Dist: pandas (==1.5.0)
Requires-Dist: pytest (==7.1.3)
Requires-Dist: scikit-learn (==1.1.2)
Requires-Dist: scipy (==1.7.3)
Requires-Dist: tqdm (==4.64.1)
Requires-Dist: pydantic (==1.10.2)
Requires-Dist: strictyaml (==1.6.2)
Requires-Dist: torch (==1.12.1)
